atom_tools/__init__.py
atom_tools/cli/__init__.py
atom_tools/cli/application.py
atom_tools/cli/command_loader.py
atom_tools/cli/logging_config.py
atom_tools/cli/commands/__init__.py
atom_tools/cli/commands/check_reachable.py
atom_tools/cli/commands/command.py
atom_tools/cli/commands/convert.py
atom_tools/cli/commands/filter.py
atom_tools/cli/commands/query_endpoints.py
atom_tools/cli/commands/validate_lines.py
atom_tools/lib/__init__.py
atom_tools/lib/converter.py
atom_tools/lib/filtering.py
atom_tools/lib/regex_utils.py
atom_tools/lib/ruby_converter.py
atom_tools/lib/ruby_semantics.py
atom_tools/lib/scala_converter.py
atom_tools/lib/slices.py
atom_tools/lib/utils.py
atom_tools/lib/validator.py
atom_tools-0.8.2.dist-info/licenses/LICENSE
atom_tools-0.8.2.dist-info/METADATA
atom_tools-0.8.2.dist-info/WHEEL
atom_tools-0.8.2.dist-info/entry_points.txt
atom_tools-0.8.2.dist-info/top_level.txt
atom_tools-0.8.2.dist-info/RECORD
