Metadata-Version: 2.4
Name: atom-tools
Version: 0.8.2
Summary: Collection of tools for use with AppThreat/atom.
Author-email: Caroline Russell <caroline@appthreat.dev>
License-Expression: MIT
Project-URL: Homepage, https://github.com/appthreat/atom-tools
Project-URL: Bug Tracker, https://github.com/appthreat/atom-tools/issues
Classifier: Programming Language :: Python :: 3.10
Classifier: Programming Language :: Python :: 3.11
Classifier: Programming Language :: Python :: 3.12
Classifier: Programming Language :: Python :: 3.13
Classifier: Intended Audience :: Developers
Classifier: Operating System :: OS Independent
Classifier: Topic :: Security
Classifier: Topic :: Utilities
Requires-Python: >=3.10
License-File: LICENSE
Requires-Dist: cleo>=1.0.0
Requires-Dist: jmespath>=1.0.0
Requires-Dist: thefuzz>=0.22.1
Requires-Dist: json-flatten>=0.3
Provides-Extra: dev
Requires-Dist: coverage; extra == "dev"
Requires-Dist: flake8; extra == "dev"
Requires-Dist: isort; extra == "dev"
Requires-Dist: mypy; extra == "dev"
Requires-Dist: pre-commit; extra == "dev"
Requires-Dist: pylint; extra == "dev"
Requires-Dist: pytest; extra == "dev"
Requires-Dist: tox; extra == "dev"
Dynamic: license-file
